datashield/__init__.py
datashield/api.py
datashield/interface.py
datashield-0.1.0.dist-info/WHEEL
datashield-0.1.0.dist-info/LICENSE.md
datashield-0.1.0.dist-info/METADATA
datashield-0.1.0.dist-info/RECORD
